tamilai/__init__.py
tamilai/cli.py
tamilai/translator.py
tamilai-0.0.2.dist-info/METADATA
tamilai-0.0.2.dist-info/WHEEL
tamilai-0.0.2.dist-info/entry_points.txt
tamilai-0.0.2.dist-info/RECORD
