Metadata-Version: 2.1
Name: TamilAI
Version: 0.0.2
Summary: An AI assistant that responds in Tamil
License: MIT
Author: Mervin Praison
Requires-Python: >=3.9,<4.0
Classifier: License :: OSI Approved :: MIT License
Classifier: Programming Language :: Python :: 3
Classifier: Programming Language :: Python :: 3.9
Classifier: Programming Language :: Python :: 3.10
Classifier: Programming Language :: Python :: 3.11
Classifier: Programming Language :: Python :: 3.12
Requires-Dist: click (>=8.1.7,<9.0.0)
Requires-Dist: openai (>=1.54.3,<2.0.0)
Requires-Dist: python-dotenv (>=1.0.1,<2.0.0)
